pyeogpr/__init__.py
pyeogpr/gee_processing.py
pyeogpr/openeo_processing.py
pyeogpr/sensors.py
pyeogpr/udf_L8_qa.py
pyeogpr/udfgpr.py
pyeogpr/udfsgolay.py
pyeogpr-2.4.7.dist-info/licenses/LICENSE
pyeogpr-2.4.7.dist-info/METADATA
pyeogpr-2.4.7.dist-info/WHEEL
pyeogpr-2.4.7.dist-info/top_level.txt
pyeogpr-2.4.7.dist-info/RECORD
