Metadata-Version: 2.4
Name: pyeogpr
Version: 2.4.7
Summary: Python based library to use Earth Observation data to retrieve biophysical maps using Gaussian Process Regression
Author: Dávid D.Kovács
Author-email: daviddkovacs@gmail.com
License-File: LICENSE
Requires-Dist: numpy
Requires-Dist: openeo
Requires-Dist: scipy
Requires-Dist: earthengine-api
Dynamic: author
Dynamic: author-email
Dynamic: description
Dynamic: description-content-type
Dynamic: license-file
Dynamic: requires-dist
Dynamic: summary
